git_patchman-1.1.dist-info/licenses/LICENSE
patchman/__init__.py
patchman/cli.py
patchman/manager.py
patchman/tui.py
git_patchman-1.1.dist-info/METADATA
git_patchman-1.1.dist-info/WHEEL
git_patchman-1.1.dist-info/entry_points.txt
git_patchman-1.1.dist-info/top_level.txt
git_patchman-1.1.dist-info/RECORD
