Metadata-Version: 2.4
Name: git-patchman
Version: 1.1
Home-page: https://github.com/byter11/git-patchman
Author: Mohsin Shaikh
Author-email: mohsinshk4026@gmail.com
License: MIT
Keywords: patch manager
Classifier: Programming Language :: Python :: 3
Classifier: License :: OSI Approved :: MIT License
Classifier: Operating System :: OS Independent
Requires-Python: >=3.6
License-File: LICENSE
Requires-Dist: PyTermGUI==7.7.2
Requires-Dist: typing_extensions==4.12.2
Requires-Dist: wcwidth==0.2.13
Dynamic: author
Dynamic: author-email
Dynamic: classifier
Dynamic: description
Dynamic: description-content-type
Dynamic: home-page
Dynamic: keywords
Dynamic: license
Dynamic: license-file
Dynamic: requires-dist
Dynamic: requires-python
